matplotlib_stream/__init__.py
matplotlib_stream/figure.py
matplotlib_stream-1.0.0.dist-info/METADATA
matplotlib_stream-1.0.0.dist-info/WHEEL
matplotlib_stream-1.0.0.dist-info/top_level.txt
matplotlib_stream-1.0.0.dist-info/RECORD
