Metadata-Version: 1.2
Name: matplotlib-stream
Version: 1.0.0
Summary: GCPDS: matplotlib stream
Home-page: UNKNOWN
Author: Yeison Cardona
Author-email: yeisoneng@gmail.com
Maintainer: Yeison Cardona
Maintainer-email: yeisoneng@gmail.com
License: BSD License
Download-URL: https://bitbucket.org/gcpds/matplotlib-stream
Platform: UNKNOWN
